flaskapi4/__init__.py
flaskapi4/__version__.py
flaskapi4/blueprint.py
flaskapi4/commands.py
flaskapi4/doc/__init__.py
flaskapi4/doc/rapidoc/__init__.py
flaskapi4/doc/rapidoc/__version__.py
flaskapi4/doc/rapidoc/plugins.py
flaskapi4/doc/rapidoc/templates/__init__.py
flaskapi4/doc/rapidoc/templates/rapidoc/images/rapidoc.svg
flaskapi4/doc/rapidoc/templates/rapidoc/js/rapidoc-min.js
flaskapi4/doc/redoc/__init__.py
flaskapi4/doc/redoc/__version__.py
flaskapi4/doc/redoc/plugins.py
flaskapi4/doc/redoc/templates/__init__.py
flaskapi4/doc/redoc/templates/redoc/images/redoc.svg
flaskapi4/doc/redoc/templates/redoc/js/redoc.standalone.js
flaskapi4/doc/scalar/__init__.py
flaskapi4/doc/scalar/__version__.py
flaskapi4/doc/scalar/plugins.py
flaskapi4/doc/scalar/templates/__init__.py
flaskapi4/doc/scalar/templates/scalar/images/scalar.svg
flaskapi4/doc/scalar/templates/scalar/js/scalar.standalone.js
flaskapi4/flaskapi.py
flaskapi4/models/__init__.py
flaskapi4/models/callback.py
flaskapi4/models/components.py
flaskapi4/models/contact.py
flaskapi4/models/data_type.py
flaskapi4/models/discriminator.py
flaskapi4/models/encoding.py
flaskapi4/models/example.py
flaskapi4/models/external_documentation.py
flaskapi4/models/file.py
flaskapi4/models/header.py
flaskapi4/models/info.py
flaskapi4/models/license.py
flaskapi4/models/link.py
flaskapi4/models/media_type.py
flaskapi4/models/oauth_flow.py
flaskapi4/models/oauth_flows.py
flaskapi4/models/operation.py
flaskapi4/models/parameter.py
flaskapi4/models/parameter_in_type.py
flaskapi4/models/path_item.py
flaskapi4/models/paths.py
flaskapi4/models/reference.py
flaskapi4/models/request_body.py
flaskapi4/models/response.py
flaskapi4/models/responses.py
flaskapi4/models/schema.py
flaskapi4/models/security_requirement.py
flaskapi4/models/security_scheme.py
flaskapi4/models/security_scheme_in_type.py
flaskapi4/models/server.py
flaskapi4/models/server_variable.py
flaskapi4/models/style_values.py
flaskapi4/models/tag.py
flaskapi4-0.1.8.dist-info/LICENSE
flaskapi4-0.1.8.dist-info/METADATA
flaskapi4-0.1.8.dist-info/WHEEL
flaskapi4-0.1.8.dist-info/RECORD
